memfo/TimeMemory.py
memfo/__init__.py
memfo/dumper.py
memfo/main.py
memfo/memfod.py
memfo-2.0.5.dist-info/entry_points.txt
memfo-2.0.5.dist-info/licenses/LICENSE
memfo-2.0.5.dist-info/WHEEL
memfo-2.0.5.dist-info/METADATA
memfo-2.0.5.dist-info/RECORD
