Metadata-Version: 2.4
Name: memfo
Version: 2.0.5
Summary: Display Tool for /proc/meminfo
Keywords: meminfo,/proc/meminfo,RAM,memory statistics
Author-email: Joe Defen <joedef@duck.com>
Requires-Python: >=3.8
Classifier: Programming Language :: Python :: 3
Classifier: License :: OSI Approved :: MIT License
Classifier: Operating System :: POSIX :: Linux
License-File: LICENSE
Requires-Dist: console-window == 1.3.2
Project-URL: Bug Tracker, https://github.com/joedefen/memfo/issues
Project-URL: Homepage, https://github.com/joedefen/memfo
